aryaxai/__init__.py
aryaxai/version.py
aryaxai/client/__init__.py
aryaxai/client/client.py
aryaxai/common/__init__.py
aryaxai/common/constants.py
aryaxai/common/enums.py
aryaxai/common/environment.py
aryaxai/common/monitoring.py
aryaxai/common/trigger.py
aryaxai/common/types.py
aryaxai/common/utils.py
aryaxai/common/validation.py
aryaxai/common/xai_uris.py
aryaxai/core/__init__.py
aryaxai/core/agent.py
aryaxai/core/alert.py
aryaxai/core/case.py
aryaxai/core/dashboard.py
aryaxai/core/model_summary.py
aryaxai/core/organization.py
aryaxai/core/project.py
aryaxai/core/synthetic.py
aryaxai/core/text.py
aryaxai/core/tracer.py
aryaxai/core/utils.py
aryaxai/core/workspace.py
aryaxai/core/wrapper.py
aryaxai/core/xai.py
aryaxai/core/guardrails/__init__.py
aryaxai/core/guardrails/guard_template.py
aryaxai/core/guardrails/guardrail_autogen.py
aryaxai/core/guardrails/guardrails_langgraph.py
aryaxai/core/guardrails/guardrails_openai.py
aryaxai/core/guardrails/openai_runner.py
aryaxai-0.0.157.dist-info/licenses/LICENSE
aryaxai-0.0.157.dist-info/METADATA
aryaxai-0.0.157.dist-info/WHEEL
aryaxai-0.0.157.dist-info/top_level.txt
aryaxai-0.0.157.dist-info/RECORD
