Metadata-Version: 2.4
Name: aryaxai
Version: 0.0.157
Summary: Full stack ML Observability with AryaXAI
Home-page: https://xai.arya.ai/docs/introduction
License: MIT
Keywords: aryaxai,ML observability
Classifier: Intended Audience :: Developers
Classifier: Intended Audience :: Science/Research
Classifier: Programming Language :: Python :: 3
Classifier: License :: OSI Approved :: MIT License
Classifier: Operating System :: OS Independent
Requires-Python: >=3.0
License-File: LICENSE
Requires-Dist: pydantic>=1.10.13
Requires-Dist: pyjwt>=2.3.0
Requires-Dist: python-dotenv>=1.0.0
Requires-Dist: requests>=2.31.0
Requires-Dist: pandas>=1.5.3
Requires-Dist: plotly>=5.15.0
Requires-Dist: ipython>=7.34.0
Requires-Dist: Pillow>=10.4.0
Requires-Dist: google-genai>=1.24.0
Requires-Dist: anthropic>=0.57.1
Requires-Dist: openai>=1.93.1
Requires-Dist: groq>=0.29.0
Requires-Dist: xai-sdk>=1.0.0
Requires-Dist: together>=1.3.14
Requires-Dist: replicate>=1.0.7
Requires-Dist: huggingface-hub>=0.33.2
Requires-Dist: mistralai>=1.9.1
Requires-Dist: boto3>=1.39.4
Requires-Dist: opentelemetry-sdk>=1.36.0
Requires-Dist: opentelemetry-exporter-otlp>=1.36.0
Requires-Dist: openinference-instrumentation-langchain>=0.1.50
Requires-Dist: openinference-instrumentation-autogen-agentchat>=0.1.4
Requires-Dist: openinference-instrumentation-crewai>=0.1.11
Requires-Dist: openinference-instrumentation-dspy>=0.1.28
Requires-Dist: openinference-instrumentation-llama-index>=4.3.4
Requires-Dist: openinference-instrumentation-openai-agents>=1.2.0
Requires-Dist: openinference-instrumentation-smolagents>=0.1.16
Dynamic: classifier
Dynamic: description
Dynamic: description-content-type
Dynamic: home-page
Dynamic: keywords
Dynamic: license
Dynamic: license-file
Dynamic: requires-dist
Dynamic: requires-python
Dynamic: summary
